kpireport_jenkins/__init__.py
kpireport_jenkins/build_summary.py
kpireport_jenkins/datasource.py
kpireport_jenkins/templates/jenkins_build_summary.html
kpireport_jenkins/templates/jenkins_build_summary.md
kpireport_jenkins/templates/jenkins_build_summary.slack
kpireport_jenkins-0.0.1.dist-info/METADATA
kpireport_jenkins-0.0.1.dist-info/WHEEL
kpireport_jenkins-0.0.1.dist-info/entry_points.txt
kpireport_jenkins-0.0.1.dist-info/top_level.txt
kpireport_jenkins-0.0.1.dist-info/RECORD
