Metadata-Version: 2.1
Name: kpireport-jenkins
Version: 0.0.1
Summary: UNKNOWN
Home-page: UNKNOWN
Author: Jason Anderson
Author-email: diurnalist@gmail.com
License: Prosperity Public License
Platform: UNKNOWN
Requires-Dist: kpireport
Requires-Dist: python-jenkins
